pixpy-0.2.0.dist-info/RECORD
pixpy-0.2.0.dist-info/WHEEL
pixpy-0.2.0.dist-info/METADATA
pixpy-0.2.0.dist-info/licenses/LICENSE.md
pixpy/color.pyi
pixpy/__init__.pyi
pixpy/_pixpy.pypy310-pp73-darwin.so
pixpy/repl.py
pixpy/__init__.py
pixpy/treesitter.pyi
pixpy/key.pyi
pixpy/event.pyi
pixpy/py.typed
pixpy/pixide.py
pixpy/HackNerdFont-Regular.ttf
pixpy/editor.py
pixpy/__main__.py
