Metadata-Version: 2.4
Name: pixpy
Version: 0.2.0
Summary: Graphics library
Author-Email: Jonas Minnberg <sasq64@gmail.com>
License-Expression: MIT
Project-URL: repository, https://github.com/sasq64/pix
Project-URL: documentation, https://pixpy.readthedocs.org
Requires-Python: >=3.9
